{
    "schema_version": "2.0",
    "customer": "NAC",
    "records": [
        {
            "invoice": "50217-2026",
            "description": "NAC Net Repair qty 12",
            "amount": 4200.0,
            "invoice_date": "2026-02-25",
            "location": "LAX",
            "category": "Repairs",
            "product": "Nets",
            "repair_quantity": 12
        },
        {
            "invoice": "50270-2026",
            "description": "ULDM INV#24000900, Cust. PO-1082649",
            "amount": 6757.9,
            "invoice_date": "2026-02-19",
            "location": "LAX",
            "category": "Distribution",
            "product": "",
            "repair_quantity": 0
        },
        {
            "invoice": "50271-2026",
            "description": "ULDM INV#24000901, Cust. PO-1082684",
            "amount": 950.0,
            "invoice_date": "2026-02-19",
            "location": "LAX",
            "category": "Distribution",
            "product": "",
            "repair_quantity": 0
        },
        {
            "invoice": "50272-2026",
            "description": "ULDM INV#24000902, Cust. PO-1082690",
            "amount": 3278.0,
            "invoice_date": "2026-02-19",
            "location": "LAX",
            "category": "Distribution",
            "product": "",
            "repair_quantity": 0
        },
        {
            "invoice": "50275-2026",
            "description": "ULDM INV#24000903, Cust. PO-1082705 & 1082716",
            "amount": 3487.45,
            "invoice_date": "2026-02-20",
            "location": "LAX",
            "category": "Distribution",
            "product": "",
            "repair_quantity": 0
        },
        {
            "invoice": "50276-2026",
            "description": "ULDM INV#24000904, Cust. PO-1082649",
            "amount": 13515.8,
            "invoice_date": "2026-02-20",
            "location": "LAX",
            "category": "Distribution",
            "product": "",
            "repair_quantity": 0
        },
        {
            "invoice": "50398-2026",
            "description": "ULDM INV#24000959, Cust. PO-1082668",
            "amount": 15861.9,
            "invoice_date": "2026-03-26",
            "location": "LAX",
            "category": "Distribution",
            "product": "",
            "repair_quantity": 0
        }
    ]
}